LICENSE.md
MANIFEST.in
README.md
setup.py
DGEclust.egg-info/PKG-INFO
DGEclust.egg-info/SOURCES.txt
DGEclust.egg-info/dependency_links.txt
DGEclust.egg-info/not-zip-safe
DGEclust.egg-info/requires.txt
DGEclust.egg-info/top_level.txt
dgeclust/__init__.py
dgeclust/config.py
dgeclust/data.py
dgeclust/manager.py
dgeclust/postprocessing.py
dgeclust/stats.py
dgeclust/utils.py
dgeclust/models/__init__.py
dgeclust/models/nbinom.py