Metadata-Version: 1.1
Name: DGEclust
Version: 15.1.29
Summary: Hierarchical non-parametric Bayesian clustering of digital expression data
Home-page: http://dvav.me/dgeclust/
Author: Dimitrios V. Vavoulis
Author-email: dimitris.vavoulis@bristol.ac.uk
License: MIT
Platform: UNIX
Classifier: Development Status :: 4 - Beta
Classifier: License :: OSI Approved :: MIT License
Classifier: Programming Language :: Python :: 2.7
Classifier: Operating System :: Unix
Classifier: Topic :: Scientific/Engineering :: Bio-Informatics
